transformer_engine/__init__.py
transformer_engine/common/__init__.py
transformer_engine/common/utils.py
transformer_engine/common/recipe/__init__.py
transformer_engine/debug/__init__.py
transformer_engine/debug/features/__init__.py
transformer_engine/debug/features/_test_dummy_feature.py
transformer_engine/debug/features/api.py
transformer_engine/debug/features/disable_fp8_gemm.py
transformer_engine/debug/features/disable_fp8_layer.py
transformer_engine/debug/features/fake_quant.py
transformer_engine/debug/features/log_fp8_tensor_stats.py
transformer_engine/debug/features/log_tensor_stats.py
transformer_engine/debug/features/per_tensor_scaling.py
transformer_engine/debug/features/utils/__init__.py
transformer_engine/debug/features/utils/stats_buffer.py
transformer_engine/debug/features/utils/stats_computation.py
transformer_engine/debug/pytorch/__init__.py
transformer_engine/debug/pytorch/debug_quantization.py
transformer_engine/debug/pytorch/debug_state.py
transformer_engine/debug/pytorch/utils.py
transformer_engine/jax/__init__.py
transformer_engine/jax/activation.py
transformer_engine/jax/attention.py
transformer_engine/jax/checkpoint_policies.py
transformer_engine/jax/dense.py
transformer_engine/jax/layernorm.py
transformer_engine/jax/layernorm_dense.py
transformer_engine/jax/layernorm_mlp.py
transformer_engine/jax/setup.py
transformer_engine/jax/sharding.py
transformer_engine/jax/softmax.py
transformer_engine/jax/cpp_extensions/__init__.py
transformer_engine/jax/cpp_extensions/activation.py
transformer_engine/jax/cpp_extensions/amax.py
transformer_engine/jax/cpp_extensions/attention.py
transformer_engine/jax/cpp_extensions/base.py
transformer_engine/jax/cpp_extensions/gemm.py
transformer_engine/jax/cpp_extensions/misc.py
transformer_engine/jax/cpp_extensions/normalization.py
transformer_engine/jax/cpp_extensions/quantization.py
transformer_engine/jax/cpp_extensions/softmax.py
transformer_engine/jax/flax/__init__.py
transformer_engine/jax/flax/module.py
transformer_engine-2.9.0.dist-info/licenses/LICENSE
transformer_engine-2.9.0.dist-info/METADATA
transformer_engine-2.9.0.dist-info/WHEEL
transformer_engine-2.9.0.dist-info/top_level.txt
transformer_engine-2.9.0.dist-info/RECORD
