Metadata-Version: 2.4
Name: transformer_engine
Version: 2.9.0
Summary: Transformer acceleration library
Classifier: Programming Language :: Python :: 3
Requires-Python: >=3.10.0
License-File: LICENSE
Provides-Extra: core
Requires-Dist: transformer_engine_cu12==2.9.0; extra == "core"
Provides-Extra: core-cu12
Requires-Dist: transformer_engine_cu12==2.9.0; extra == "core-cu12"
Provides-Extra: core-cu13
Requires-Dist: transformer_engine_cu13==2.9.0; extra == "core-cu13"
Provides-Extra: pytorch
Requires-Dist: transformer_engine_torch==2.9.0; extra == "pytorch"
Provides-Extra: jax
Requires-Dist: transformer_engine_jax==2.9.0; extra == "jax"
Dynamic: classifier
Dynamic: description
Dynamic: description-content-type
Dynamic: license-file
Dynamic: provides-extra
Dynamic: requires-python
Dynamic: summary
